{
  "buildFiles": [
    "C:\\dev\\flutter\\packages\\flutter_tools\\gradle\\src\\main\\groovy\\CMakeLists.txt"
  ],
  "cleanCommandsComponents": [
    [
      "C:\\Users\\alaa\\AppData\\Local\\Android\\sdk\\cmake\\3.22.1\\bin\\ninja.exe",
      "-C",
      "C:\\Users\\alaa\\Desktop\\Graduation Project\\Wqaya\\android\\app\\.cxx\\RelWithDebInfo\\x5a6126d\\x86",
      "clean"
    ]
  ],
  "buildTargetsCommandComponents": [
    "C:\\Users\\alaa\\AppData\\Local\\Android\\sdk\\cmake\\3.22.1\\bin\\ninja.exe",
    "-C",
    "C:\\Users\\alaa\\Desktop\\Graduation Project\\Wqaya\\android\\app\\.cxx\\RelWithDebInfo\\x5a6126d\\x86",
    "{LIST_OF_TARGETS_TO_BUILD}"
  ],
  "libraries": {},
  "toolchains": {
    "toolchain": {
      "cCompilerExecutable": "C:\\Users\\alaa\\AppData\\Local\\Android\\Sdk\\ndk\\26.3.11579264\\toolchains\\llvm\\prebuilt\\windows-x86_64\\bin\\clang.exe",
      "cppCompilerExecutable": "C:\\Users\\alaa\\AppData\\Local\\Android\\Sdk\\ndk\\26.3.11579264\\toolchains\\llvm\\prebuilt\\windows-x86_64\\bin\\clang++.exe"
    }
  },
  "cFileExtensions": [],
  "cppFileExtensions": []
}